dp_cgans/__init__.py
dp_cgans/__main__.py
dp_cgans/base.py
dp_cgans/data_sampler.py
dp_cgans/data_transformer.py
dp_cgans/dp_cgan_init.py
dp_cgans/errors.py
dp_cgans/rdp_accountant.py
dp_cgans/constraints/__init__.py
dp_cgans/constraints/base.py
dp_cgans/constraints/errors.py
dp_cgans/constraints/tabular.py
dp_cgans/constraints/utils.py
dp_cgans/metadata/__init__.py
dp_cgans/metadata/dataset.py
dp_cgans/metadata/errors.py
dp_cgans/metadata/table.py
dp_cgans/metadata/utils.py
dp_cgans/metadata/visualization.py
dp_cgans/synthesizers/__init__.py
dp_cgans/synthesizers/base.py
dp_cgans/synthesizers/dp_cgan.py
dp_cgans-0.0.6.dist-info/METADATA
dp_cgans-0.0.6.dist-info/WHEEL
dp_cgans-0.0.6.dist-info/entry_points.txt
dp_cgans-0.0.6.dist-info/licenses/LICENSE.txt
dp_cgans-0.0.6.dist-info/RECORD
