Metadata-Version: 2.1
Name: dp-cgans
Version: 0.0.6
Summary: A library to generate synthetic tabular or RDF data using Conditional Generative Adversary Networks (GANs) combined with Differential Privacy techniques.
Project-URL: Homepage, https://github.com/sunchang0124/dp_cgans
Project-URL: Documentation, https://github.com/sunchang0124/dp_cgans
Project-URL: History, https://github.com/sunchang0124/dp_cgans/releases
Project-URL: Tracker, https://github.com/sunchang0124/dp_cgans/issues
Project-URL: Source, https://github.com/sunchang0124/dp_cgans
Author-email: Sun Chang <sunchang0124@gmail.com>
Maintainer-email: Sun Chang <sunchang0124@gmail.com>, Vincent Emonet <vincent.emonet@gmail.com>
License: MIT License
License-File: LICENSE.txt
Keywords: CGAN,DP,Differential Privacy,GAN,synthetic data
Classifier: License :: OSI Approved :: MIT License
Classifier: Operating System :: OS Independent
Classifier: Programming Language :: Python :: 3
Classifier: Programming Language :: Python :: 3.8
Classifier: Programming Language :: Python :: 3.9
Classifier: Programming Language :: Python :: 3.10
Classifier: Programming Language :: Python :: 3.11
Requires-Python: >=3.8
Requires-Dist: copulas
Requires-Dist: graphviz
Requires-Dist: numpy
Requires-Dist: pandas
Requires-Dist: pyreadstat
Requires-Dist: rdt
Requires-Dist: scikit-learn
Requires-Dist: scipy
Requires-Dist: sdv>=1.5.0
Requires-Dist: torch
Requires-Dist: typed-ast
Requires-Dist: typer
Requires-Dist: wandb
Provides-Extra: test
Requires-Dist: black; extra == 'test'
Requires-Dist: mypy>=1.4.1; extra == 'test'
Requires-Dist: pip-tools; extra == 'test'
Requires-Dist: pytest-cov>=3.0.0; extra == 'test'
Requires-Dist: pytest>=7.4.0; extra == 'test'
Requires-Dist: ruff; extra == 'test'
Requires-Dist: types-pyyaml; extra == 'test'
Requires-Dist: types-requests; extra == 'test'
